external_link/__init__.py
external_link/handlers.py
external_link/wagtail_hooks.py
external_link/migrations/__init__.py
wagtail_external_link_richtext-1.1.4.dist-info/LICENSE
wagtail_external_link_richtext-1.1.4.dist-info/METADATA
wagtail_external_link_richtext-1.1.4.dist-info/WHEEL
wagtail_external_link_richtext-1.1.4.dist-info/top_level.txt
wagtail_external_link_richtext-1.1.4.dist-info/RECORD
