Metadata-Version: 2.1
Name: wagtail-external-link-richtext
Version: 1.1.4
Summary: A feature for the richtext fields in Wagtail
Author-email: Ruben Hesselink <ruben@fourdigits.nl>
License: Copyright 2023 Four Digits
Project-URL: Homepage, https://github.com/fourdigits/wagtail-external-richtext-link
Keywords: richtext,external,link,wagtail,newtab,django
Classifier: Environment :: Web Environment
Classifier: Framework :: Wagtail
Classifier: Framework :: Django
Classifier: Intended Audience :: Developers
Classifier: License :: OSI Approved :: MIT License
Classifier: Programming Language :: Python
Classifier: Programming Language :: Python :: 3.8
Classifier: Programming Language :: Python :: 3.9
Classifier: Programming Language :: Python :: 3.10
Classifier: Programming Language :: Python :: 3.11
Classifier: Programming Language :: Python :: 3.12
Requires-Python: >=3.8
License-File: LICENSE
Requires-Dist: Django >=3.2
Requires-Dist: wagtail >=3.0
Provides-Extra: test
Requires-Dist: pytest ; extra == 'test'
Requires-Dist: pytest-django ; extra == 'test'
